README.md
setup.py
bswiader_hello_world.egg-info/PKG-INFO
bswiader_hello_world.egg-info/SOURCES.txt
bswiader_hello_world.egg-info/dependency_links.txt
bswiader_hello_world.egg-info/top_level.txt
sample_package/__init__.py
sample_package/sample.py